<?xml version="1.0" encoding="UTF-8" ?><xml><records><record><database name="SOEPlit_master.enl" path="U:\SOEPLIT\Endnote\SOEPlit_master.enl">SOEPlit_master.enl</database><source-app name="EndNote" version="17.0">EndNote</source-app><rec-number>13546</rec-number><foreign-keys><key app="EN" db-id="sw9fd25xqxxt0xep9fbpf9zqrtpe5t9wz0wv">13546</key></foreign-keys><ref-type name="Journal Article">17</ref-type><contributors><authors><author><style face="normal" font="default" size="100%">Luechinger, Simon</style></author><author><style face="normal" font="default" size="100%">Stutzer, Alois</style></author><author><style face="normal" font="default" size="100%">Winkelmann, Rainer</style></author></authors></contributors><titles><title><style face="normal" font="default" size="100%">Self-selection models for public and private sector job satisfaction</style></title><secondary-title><style face="normal" font="default" size="100%">Research in Labor Economics</style></secondary-title></titles><pages><style face="normal" font="default" size="100%">233-251</style></pages><volume><style face="normal" font="default" size="100%">30</style></volume><dates><year><style face="normal" font="default" size="100%">2013</style></year></dates><accession-num><style face="normal" font="default" size="100%">8097</style></accession-num><abstract><style face="normal" font="default" size="100%">We discuss a class of copula-based ordered probit models with endogenous switching. Such models can be useful for the analysis of self-selection in subjective well-being equations in general, and job satisfaction in particular, where assignment of regressors may be endogenous rather than random, resulting from individual maximization of well-being. In an application to public and private sector job satisfaction, and using data on male workers from the German Socio-Economic Panel for 2004, and using two alternative copula functions for dependence, we find consistent evidence for endogenous sector selection.</style></abstract><label><style face="normal" font="default" size="100%">labour, subjective indicators</style></label><urls><related-urls><url><style face="normal" font="default" size="100%">http://www.zora.uzh.ch/35270/2/Luechinger_Stutz_Winkelmann-self-selection_models-2010.pdf</style></url></related-urls><pdf-urls><url>file://U:\SOEPLIT\Dokumente\8097.pdf</url></pdf-urls></urls><custom2><style face="normal" font="default" size="100%">cross-sectional</style></custom2><custom4><style face="normal" font="default" size="100%">T02, T08</style></custom4><custom5><style face="normal" font="default" size="100%">02 SSCI Journal</style></custom5><custom7><style face="normal" font="default" size="100%">Wirtschaftswissenschaften</style></custom7><electronic-resource-num><style face="normal" font="default" size="100%">10.1108/S0147-9121(2010)0000030010</style></electronic-resource-num><remote-database-name><style face="normal" font="default" size="100%">INLA</style></remote-database-name><remote-database-provider><style face="normal" font="default" size="100%">SOEP</style></remote-database-provider><language><style face="normal" font="default" size="100%">GB</style></language></record><record><database name="SOEPlit_master.enl" path="U:\SOEPLIT\Endnote\SOEPlit_master.enl">SOEPlit_master.enl</database><source-app name="EndNote" version="17.0">EndNote</source-app><rec-number>13544</rec-number><foreign-keys><key app="EN" db-id="sw9fd25xqxxt0xep9fbpf9zqrtpe5t9wz0wv">13544</key></foreign-keys><ref-type name="Journal Article">17</ref-type><contributors><authors><author><style face="normal" font="default" size="100%">Headey, Bruce</style></author><author><style face="normal" font="default" size="100%">Hoehne, Gerhard</style></author><author><style face="normal" font="default" size="100%">Wagner, Gert G.</style></author></authors></contributors><titles><title><style face="normal" font="default" size="100%">Does Religion Make You Healthier and Longer Lived? Evidence for Germany</style></title><secondary-title><style face="normal" font="default" size="100%">Social Indicators Research</style></secondary-title></titles><volume><style face="normal" font="default" size="100%">(online first)</style></volume><dates><year><style face="normal" font="default" size="100%">2013</style></year></dates><accession-num><style face="normal" font="default" size="100%">8095</style></accession-num><abstract><style face="normal" font="default" size="100%">Researchers in the US have consistently reported substantial—not just statistically significant—links between religious belief and practice, and improved health and longevity. In this paper we report evidence for Germany, using data from the long-running, nationally representative German Socio-Economic Panel (SOEP 1984). The SOEP dataset includes multiple measures of health, plus many ‘controls’ which it is appropriate to use in assessing links between religious practice, health and longevity. These controls include personality traits known to be associated with better health (notably conscientiousness), and also the age of death of parents of the survey respondents. Initial results suggested that religious practice (church attendance) may be linked only to subjective (self-rated) measures of health, not to more objective measures. It seemed possible that results in some previous research could be due to what may be termed satisfaction bias or positivity bias; the known tendency of religious people to report higher than average satisfaction with almost all aspects of life. Further investigation indicated that relationships between church attendance and subjective measures of health were weaker, when a control for satisfaction bias was in place. However, there was countervailing evidence that the subjective measures in SOEP may actually be more not less valid than the objective measures; they are better not worse predictors of mortality. It was also clear that religious belief and church attendance are associated with health-protective behaviors and attitudes, including taking more exercise, not smoking and higher life satisfaction. At the end of the paper we estimate a structural equation model which maps links between religious practice, these protective behaviors and attitudes, and improved health outcomes.</style></abstract><label><style face="normal" font="default" size="100%">health, subjective indicators</style></label><urls><pdf-urls><url>file://U:\SOEPLIT\Dokumente\8095_c.pdf</url></pdf-urls></urls><custom2><style face="normal" font="default" size="100%">longitudinal</style></custom2><custom4><style face="normal" font="default" size="100%">T05, T08</style></custom4><custom5><style face="normal" font="default" size="100%">02 SSCI Journal</style></custom5><electronic-resource-num><style face="normal" font="default" size="100%">10.1007/s11205-013-0546-x</style></electronic-resource-num><remote-database-name><style face="normal" font="default" size="100%">SOEP</style></remote-database-name><remote-database-provider><style face="normal" font="default" size="100%">SOEP</style></remote-database-provider><language><style face="normal" font="default" size="100%">GB</style></language></record><record><database name="SOEPlit_master.enl" path="U:\SOEPLIT\Endnote\SOEPlit_master.enl">SOEPlit_master.enl</database><source-app name="EndNote" version="17.0">EndNote</source-app><rec-number>13541</rec-number><foreign-keys><key app="EN" db-id="sw9fd25xqxxt0xep9fbpf9zqrtpe5t9wz0wv">13541</key></foreign-keys><ref-type name="Report">27</ref-type><contributors><authors><author><style face="normal" font="default" size="100%">Kröll, Alexandra</style></author><author><style face="normal" font="default" size="100%">Borck, Rainald</style></author></authors></contributors><titles><title><style face="normal" font="default" size="100%">The Influence of Child Care on Maternal Health and Mother-Child Interaction</style></title><secondary-title><style face="normal" font="default" size="100%">SOEPpapers 615</style></secondary-title><translated-title><style face="normal" font="default" size="100%">http://www.cesifo-group.de/DocDL/cesifo1_wp4289.pdf</style></translated-title></titles><dates><year><style face="normal" font="default" size="100%">2013</style></year></dates><pub-location><style face="normal" font="default" size="100%">Berlin</style></pub-location><publisher><style face="normal" font="default" size="100%">DIW Berlin</style></publisher><orig-pub><style face="normal" font="default" size="100%">2013:CESifo Working Paper No. 4289</style></orig-pub><accession-num><style face="normal" font="default" size="100%">8092</style></accession-num><abstract><style face="normal" font="default" size="100%">In Germany, formal child care coverage rates have increased markedly over the past few decades. The expansion in coverage is particularly pronounced for under 3 year-olds. The present paper is concerned with how mothers’ mental and physical health is affected by whether they place their child in formal day care or not. Furthermore, the effects of formal child care usage on mother-child interaction are examined. The analysis is based on data from the German Socio-Economic Panel for the years 2006 to 2010. This data is analysed by means of regression analyses, using local aggregate formal child care usage rates as an instrument for individual formal child care usage. The results indicate that mothers are in a worse physical condition if their children attend formal care, whereas no such effect is found with regard to mothers’ mental health. Overall, there is evidence that mothers placing their children in formal care interact with them more frequently.</style></abstract><label><style face="normal" font="default" size="100%">family and networks, health, education</style></label><urls><related-urls><url><style face="normal" font="default" size="100%">http://www.diw.de/documents/publikationen/73/diw_01.c.434130.de/diw_sp0615.pdf</style></url></related-urls><pdf-urls><url>file://U:\SOEPLIT\Dokumente\8092.pdf</url></pdf-urls></urls><custom2><style face="normal" font="default" size="100%">longitudinal</style></custom2><custom4><style face="normal" font="default" size="100%">T04, T05, T07</style></custom4><custom5><style face="normal" font="default" size="100%">32 SOEPpaper</style></custom5><custom6><style face="normal" font="default" size="100%">615</style></custom6><custom7><style face="normal" font="default" size="100%">Wirtschaftswissenschaften</style></custom7><remote-database-name><style face="normal" font="default" size="100%">INLA</style></remote-database-name><remote-database-provider><style face="normal" font="default" size="100%">SOEP</style></remote-database-provider><language><style face="normal" font="default" size="100%">GB</style></language></record><record><database name="SOEPlit_master.enl" path="U:\SOEPLIT\Endnote\SOEPlit_master.enl">SOEPlit_master.enl</database><source-app name="EndNote" version="17.0">EndNote</source-app><rec-number>13508</rec-number><foreign-keys><key app="EN" db-id="sw9fd25xqxxt0xep9fbpf9zqrtpe5t9wz0wv">13508</key></foreign-keys><ref-type name="Book Section">5</ref-type><contributors><authors><author><style face="normal" font="default" size="100%">Alscher, Mareike</style></author><author><style face="normal" font="default" size="100%">Priller, Eckard</style></author></authors><secondary-authors><author><style face="normal" font="default" size="100%">Statistisches Bundesamt</style></author><author><style face="normal" font="default" size="100%">Wissenschaftszentrum Berlin für Sozialforschung (WZB)</style></author><author><style face="normal" font="default" size="100%">Das Sozio-oekonomische Panel am Deutschen Institut für Wirtschaftsforschung (DIW)</style></author></secondary-authors></contributors><titles><title><style face="normal" font="default" size="100%">Zivilgesellschaftliches Engagement (Kap. 12.3)</style></title><secondary-title><style face="normal" font="default" size="100%">Datenreport 2013. Ein Sozialbericht für die Bundesrepublik Deutschland</style></secondary-title></titles><pages><style face="normal" font="default" size="100%">350-356</style></pages><dates><year><style face="normal" font="default" size="100%">2013</style></year></dates><pub-location><style face="normal" font="default" size="100%">Bonn</style></pub-location><publisher><style face="normal" font="default" size="100%">Bundeszentrale für politische Bildung</style></publisher><accession-num><style face="normal" font="default" size="100%">8064</style></accession-num><call-num><style face="normal" font="default" size="100%">WAHR</style></call-num><label><style face="normal" font="default" size="100%">subjective indicators</style></label><notes><style face="normal" font="default" size="100%">Politik</style></notes><urls><related-urls><url><style face="normal" font="default" size="100%">http://www.wzb.eu/sites/default/files/u6/12_freizeit_und_gesellschaftliche_partizipation.pdf</style></url></related-urls><pdf-urls><url>file://U:\SOEPLIT\Dokumente\8064.pdf</url></pdf-urls></urls><custom2><style face="normal" font="default" size="100%">longitudinal</style></custom2><custom4><style face="normal" font="default" size="100%">T09, T08</style></custom4><custom5><style face="normal" font="default" size="100%">20 Book Section</style></custom5><remote-database-name><style face="normal" font="default" size="100%">INLA</style></remote-database-name><remote-database-provider><style face="normal" font="default" size="100%">SOEP</style></remote-database-provider><language><style face="normal" font="default" size="100%">D</style></language></record><record><database name="SOEPlit_master.enl" path="U:\SOEPLIT\Endnote\SOEPlit_master.enl">SOEPlit_master.enl</database><source-app name="EndNote" version="17.0">EndNote</source-app><rec-number>13497</rec-number><foreign-keys><key app="EN" db-id="sw9fd25xqxxt0xep9fbpf9zqrtpe5t9wz0wv">13497</key></foreign-keys><ref-type name="Magazine Article">19</ref-type><contributors><authors><author><style face="normal" font="default" size="100%">o.V.,</style></author></authors></contributors><titles><title><style face="normal" font="default" size="100%">Mindestlohn: Viel Wunschdenken</style></title><secondary-title><style face="normal" font="default" size="100%">iwd</style></secondary-title></titles><pages><style face="normal" font="default" size="100%">3</style></pages><volume><style face="normal" font="default" size="100%">39</style></volume><number><style face="normal" font="default" size="100%">46</style></number><dates><year><style face="normal" font="default" size="100%">2013</style></year></dates><accession-num><style face="normal" font="default" size="100%">8053</style></accession-num><abstract><style face="normal" font="default" size="100%">In den Berliner Koalitionsverhandlungen will die SPD einen allgemeinen gesetzlichen Mindestlohn von 8,50 Euro je Stunde durchsetzen. Von den Vorteilen, die eine solche Regelung angeblich hätte, bleibt jedoch bei näherem Hinsehen wenig übrig. Vielmehr sind negative Wirkungen auf den Arbeitsmarkt wahrscheinlich.</style></abstract><notes><style face="normal" font="default" size="100%">Politik</style></notes><urls><pdf-urls><url>file://U:\SOEPLIT\Dokumente\8053_c.pdf</url></pdf-urls></urls><custom2><style face="normal" font="default" size="100%">citation of SOEP results</style></custom2><custom5><style face="normal" font="default" size="100%">62 Professional Newsletter</style></custom5><remote-database-name><style face="normal" font="default" size="100%">ZITA</style></remote-database-name><language><style face="normal" font="default" size="100%">D</style></language></record><record><database name="SOEPlit_master.enl" path="U:\SOEPLIT\Endnote\SOEPlit_master.enl">SOEPlit_master.enl</database><source-app name="EndNote" version="17.0">EndNote</source-app><rec-number>13489</rec-number><foreign-keys><key app="EN" db-id="sw9fd25xqxxt0xep9fbpf9zqrtpe5t9wz0wv">13489</key></foreign-keys><ref-type name="Book Section">5</ref-type><contributors><authors><author><style face="normal" font="default" size="100%">Richter, David</style></author><author><style face="normal" font="default" size="100%">Weinhardt, Michael</style></author></authors><secondary-authors><author><style face="normal" font="default" size="100%">Kemper, Christoph J.</style></author><author><style face="normal" font="default" size="100%">Brähler, Elmar</style></author><author><style face="normal" font="default" size="100%">Zenger, Markus</style></author></secondary-authors></contributors><titles><title><style face="normal" font="default" size="100%">RA-S: Risk Aversion-SOEP</style></title><secondary-title><style face="normal" font="default" size="100%">Psychologische und sozialwissenschaftliche Kurzskalen: Standardisierte Erhebungsinstrumente für Wissenschaft und Praxis</style></secondary-title></titles><pages><style face="normal" font="default" size="100%">258-260</style></pages><dates><year><style face="normal" font="default" size="100%">2013</style></year></dates><pub-location><style face="normal" font="default" size="100%">Berlin</style></pub-location><publisher><style face="normal" font="default" size="100%">Medizinisch Wissenschaftliche Verlagsgesellschaft (MWV)</style></publisher><accession-num><style face="normal" font="default" size="100%">8045</style></accession-num><label><style face="normal" font="default" size="100%">methods</style></label><urls><pdf-urls><url>file://U:\SOEPLIT\Dokumente\8045_c.pdf</url></pdf-urls></urls><custom2><style face="normal" font="default" size="100%">technical documentation</style></custom2><custom4><style face="normal" font="default" size="100%">T11</style></custom4><custom5><style face="normal" font="default" size="100%">20 Book Section</style></custom5><custom7><style face="normal" font="default" size="100%">Psychologie, Sozialwissenschaften</style></custom7><remote-database-name><style face="normal" font="default" size="100%">SOEP</style></remote-database-name><remote-database-provider><style face="normal" font="default" size="100%">SOEP</style></remote-database-provider><language><style face="normal" font="default" size="100%">D</style></language></record><record><database name="SOEPlit_master.enl" path="U:\SOEPLIT\Endnote\SOEPlit_master.enl">SOEPlit_master.enl</database><source-app name="EndNote" version="17.0">EndNote</source-app><rec-number>13464</rec-number><foreign-keys><key app="EN" db-id="sw9fd25xqxxt0xep9fbpf9zqrtpe5t9wz0wv">13464</key></foreign-keys><ref-type name="Book">6</ref-type><contributors><authors><author><style face="normal" font="default" size="100%">Hajek, André</style></author></authors></contributors><titles><title><style face="normal" font="default" size="100%">Der Einfluss von Armut und Reichtum auf die Lebenszufriedenheit (Dissertation)</style></title></titles><dates><year><style face="normal" font="default" size="100%">2013</style></year></dates><pub-location><style face="normal" font="default" size="100%">München</style></pub-location><publisher><style face="normal" font="default" size="100%">Utz Verlag</style></publisher><accession-num><style face="normal" font="default" size="100%">8021</style></accession-num><call-num><style face="normal" font="default" size="100%">WAHR</style></call-num><label><style face="normal" font="default" size="100%">income and poverty, subjective indicators</style></label><urls><pdf-urls><url>file://U:\SOEPLIT\Dokumente\8021.pdf</url></pdf-urls></urls><custom2><style face="normal" font="default" size="100%">longitudinal</style></custom2><custom4><style face="normal" font="default" size="100%">T03, T08</style></custom4><custom5><style face="normal" font="default" size="100%">12 Published Dissertation</style></custom5><remote-database-name><style face="normal" font="default" size="100%">INLA</style></remote-database-name><remote-database-provider><style face="normal" font="default" size="100%">SOEP</style></remote-database-provider><language><style face="normal" font="default" size="100%">D</style></language></record><record><database name="SOEPlit_master.enl" path="U:\SOEPLIT\Endnote\SOEPlit_master.enl">SOEPlit_master.enl</database><source-app name="EndNote" version="17.0">EndNote</source-app><rec-number>13443</rec-number><foreign-keys><key app="EN" db-id="sw9fd25xqxxt0xep9fbpf9zqrtpe5t9wz0wv">13443</key></foreign-keys><ref-type name="Thesis">32</ref-type><contributors><authors><author><style face="normal" font="default" size="100%">Landgraf, Daniel</style></author></authors></contributors><titles><title><style face="normal" font="default" size="100%">Owner-Occupied Housing in Germany: The Impact of Housing Policy on Household Tenure and Relocation Choice (Dissertation)</style></title></titles><dates><year><style face="normal" font="default" size="100%">2013</style></year></dates><pub-location><style face="normal" font="default" size="100%">Wiesbaden</style></pub-location><publisher><style face="normal" font="default" size="100%">EBS Universität für Wirtschaft und Recht</style></publisher><accession-num><style face="normal" font="default" size="100%">8001</style></accession-num><call-num><style face="normal" font="default" size="100%">WAHR</style></call-num><label><style face="normal" font="default" size="100%">income and poverty, consumption / assets / habitation</style></label><urls></urls><custom2><style face="normal" font="default" size="100%">longitudinal</style></custom2><custom4><style face="normal" font="default" size="100%">T03, T06</style></custom4><custom5><style face="normal" font="default" size="100%">42 Dissertation</style></custom5><custom7><style face="normal" font="default" size="100%">Wirtschaftswissenschaften</style></custom7><remote-database-name><style face="normal" font="default" size="100%">INLA</style></remote-database-name><remote-database-provider><style face="normal" font="default" size="100%">SOEP</style></remote-database-provider><language><style face="normal" font="default" size="100%">GB</style></language></record><record><database name="SOEPlit_master.enl" path="U:\SOEPLIT\Endnote\SOEPlit_master.enl">SOEPlit_master.enl</database><source-app name="EndNote" version="17.0">EndNote</source-app><rec-number>13429</rec-number><foreign-keys><key app="EN" db-id="sw9fd25xqxxt0xep9fbpf9zqrtpe5t9wz0wv">13429</key></foreign-keys><ref-type name="Report">27</ref-type><contributors><authors><author><style face="normal" font="default" size="100%">Bundesregierung</style></author></authors></contributors><titles><title><style face="normal" font="default" size="100%">Teilhabebericht der Bundesregierung über die Lebenslagen von Menschen mit Beeinträchtigungen</style></title><secondary-title><style face="normal" font="default" size="100%">Bundestags-Drucksache 17/14476</style></secondary-title></titles><dates><year><style face="normal" font="default" size="100%">2013</style></year></dates><pub-location><style face="normal" font="default" size="100%">Berlin</style></pub-location><publisher><style face="normal" font="default" size="100%">Deutscher Bundestag</style></publisher><accession-num><style face="normal" font="default" size="100%">7988</style></accession-num><label><style face="normal" font="default" size="100%">health, subjective indicators</style></label><caption><style face="normal" font="default" size="100%">x</style></caption><notes><style face="normal" font="default" size="100%">Politik</style></notes><urls><related-urls><url><style face="normal" font="default" size="100%">http://www.bmas.de/SharedDocs/Downloads/DE/PDF-Meldungen/2013-07-31-teilhabebericht.pdf?__blob=publicationFile</style></url></related-urls><pdf-urls><url>file://U:\SOEPLIT\Dokumente\7988.pdf</url></pdf-urls></urls><custom2><style face="normal" font="default" size="100%">cross-sectional</style></custom2><custom4><style face="normal" font="default" size="100%">T05, T02, T04, T07, T08</style></custom4><custom5><style face="normal" font="default" size="100%">33 Other Grey Literature</style></custom5><remote-database-name><style face="normal" font="default" size="100%">INLA</style></remote-database-name><remote-database-provider><style face="normal" font="default" size="100%">SOEP, GEDA</style></remote-database-provider><language><style face="normal" font="default" size="100%">D</style></language></record><record><database name="SOEPlit_master.enl" path="U:\SOEPLIT\Endnote\SOEPlit_master.enl">SOEPlit_master.enl</database><source-app name="EndNote" version="17.0">EndNote</source-app><rec-number>13388</rec-number><foreign-keys><key app="EN" db-id="sw9fd25xqxxt0xep9fbpf9zqrtpe5t9wz0wv">13388</key></foreign-keys><ref-type name="Report">27</ref-type><contributors><authors><author><style face="normal" font="default" size="100%">TNS Infratest Sozialforschung, </style></author></authors></contributors><titles><title><style face="normal" font="default" size="100%">SOEP 2010 - Erhebungsinstrumente 2010 (Welle 27) des Sozio-oekonomischen Panels</style></title><secondary-title><style face="normal" font="default" size="100%">SOEP Survey Papers 107: Series A</style></secondary-title><translated-title><style face="normal" font="default" size="100%">http://panel.gsoep.de/soep-docs/surveypapers/diw_ssp0107.pdf </style></translated-title></titles><dates><year><style face="normal" font="default" size="100%">2012</style></year></dates><pub-location><style face="normal" font="default" size="100%">München</style></pub-location><publisher><style face="normal" font="default" size="100%">Infratest Sozialforschung</style></publisher><orig-pub><style face="normal" font="default" size="100%">2010: München</style></orig-pub><accession-num><style face="normal" font="default" size="100%">7950</style></accession-num><call-num><style face="normal" font="default" size="100%">WAHR</style></call-num><label><style face="normal" font="default" size="100%">methods</style></label><urls><related-urls><url><style face="normal" font="default" size="100%">http://hdl.handle.net/10419/61596</style></url></related-urls><pdf-urls><url>file://U:\SOEPSurveyPapers\A_SurveyInstruments\Fertig\diw_ssp0107.pdf</url></pdf-urls></urls><custom2><style face="normal" font="default" size="100%">technical documentation</style></custom2><custom4><style face="normal" font="default" size="100%">T11</style></custom4><custom5><style face="normal" font="default" size="100%">36 Infratest Report</style></custom5><custom6><style face="normal" font="default" size="100%">S107</style></custom6><remote-database-name><style face="normal" font="default" size="100%">FELD</style></remote-database-name><language><style face="normal" font="default" size="100%">D</style></language></record><record><database name="SOEPlit_master.enl" path="U:\SOEPLIT\Endnote\SOEPlit_master.enl">SOEPlit_master.enl</database><source-app name="EndNote" version="17.0">EndNote</source-app><rec-number>13354</rec-number><foreign-keys><key app="EN" db-id="sw9fd25xqxxt0xep9fbpf9zqrtpe5t9wz0wv">13354</key></foreign-keys><ref-type name="Magazine Article">19</ref-type><contributors><authors><author><style face="normal" font="default" size="100%">Schrader, Christopher</style></author></authors></contributors><titles><title><style face="normal" font="default" size="100%">Das Auf und Ab im Leben</style></title><secondary-title><style face="normal" font="default" size="100%">Süddeutsche Zeitung vom 24. September 2013</style></secondary-title></titles><pages><style face="normal" font="default" size="100%">20</style></pages><dates><year><style face="normal" font="default" size="100%">2013</style></year></dates><accession-num><style face="normal" font="default" size="100%">7921</style></accession-num><abstract><style face="normal" font="default" size="100%">Ob Menschen glücklich sind, erkunden Sozialforscher meist, indem sie nach der Zufriedenheit fragen. Doch das wahre Bild des Lebens liefern erst Langzeitstudien, die auch Emotionen und Charakter erheben.</style></abstract><urls><pdf-urls><url>file://U:\SOEPLIT\Dokumente\7921.pdf</url></pdf-urls></urls><custom2><style face="normal" font="default" size="100%">citation of SOEP results</style></custom2><custom5><style face="normal" font="default" size="100%">60 Popular Publication</style></custom5><remote-database-name><style face="normal" font="default" size="100%">ZITA</style></remote-database-name><language><style face="normal" font="default" size="100%">D</style></language></record><record><database name="SOEPlit_master.enl" path="U:\SOEPLIT\Endnote\SOEPlit_master.enl">SOEPlit_master.enl</database><source-app name="EndNote" version="17.0">EndNote</source-app><rec-number>13337</rec-number><foreign-keys><key app="EN" db-id="sw9fd25xqxxt0xep9fbpf9zqrtpe5t9wz0wv">13337</key></foreign-keys><ref-type name="Magazine Article">19</ref-type><contributors><authors><author><style face="normal" font="default" size="100%">Kortmann, Kathryn</style></author></authors></contributors><titles><title><style face="normal" font="default" size="100%">Der letzte Schnappschuss der DDR</style></title><secondary-title><style face="normal" font="default" size="100%">Bild der Wissenschaft</style></secondary-title></titles><pages><style face="normal" font="default" size="100%">78-81</style></pages><volume><style face="normal" font="default" size="100%">50</style></volume><number><style face="normal" font="default" size="100%">10</style></number><dates><year><style face="normal" font="default" size="100%">2013</style></year></dates><accession-num><style face="normal" font="default" size="100%">7909</style></accession-num><urls></urls><custom2><style face="normal" font="default" size="100%">citation of SOEP results</style></custom2><custom5><style face="normal" font="default" size="100%">61 Popular Science Publication</style></custom5><remote-database-name><style face="normal" font="default" size="100%">ZITA</style></remote-database-name><language><style face="normal" font="default" size="100%">D</style></language></record><record><database name="SOEPlit_master.enl" path="U:\SOEPLIT\Endnote\SOEPlit_master.enl">SOEPlit_master.enl</database><source-app name="EndNote" version="17.0">EndNote</source-app><rec-number>13283</rec-number><foreign-keys><key app="EN" db-id="sw9fd25xqxxt0xep9fbpf9zqrtpe5t9wz0wv">13283</key></foreign-keys><ref-type name="Journal Article">17</ref-type><contributors><authors><author><style face="normal" font="default" size="100%">Kunzmann, Ute</style></author><author><style face="normal" font="default" size="100%">Richter, David</style></author><author><style face="normal" font="default" size="100%">Schmukle, Stefan C.</style></author></authors></contributors><titles><title><style face="normal" font="default" size="100%">Stability and Change in Affective Experience Across the Adult Life Span: Analyses With a National Sample From Germany</style></title><secondary-title><style face="normal" font="default" size="100%">Emotion</style></secondary-title><translated-title><style face="normal" font="default" size="100%">http://www.diw.de/documents/publikationen/73/diw_01.c.427642.de/diw_sp0584.pdf</style></translated-title></titles><pages><style face="normal" font="default" size="100%">1086-1095</style></pages><volume><style face="normal" font="default" size="100%">13</style></volume><number><style face="normal" font="default" size="100%">6</style></number><dates><year><style face="normal" font="default" size="100%">2013</style></year></dates><orig-pub><style face="normal" font="default" size="100%">2013: SOEPpapers 584. Berlin: DIW Berlin</style></orig-pub><accession-num><style face="normal" font="default" size="100%">7846</style></accession-num><abstract><style face="normal" font="default" size="100%">Using cross-sectional and longitudinal data from a national sample spanning the adult life span, age differences in anger and sadness were explored. The cross-sectional and longitudinal findings consistently suggest that the frequency of anger increases during young adulthood, but then shows a steady decrease until old age. By contrast, the frequency of sadness remains stable over most of adulthood and begins to increase in old age. In addition, the effects of age on happiness were investigated; the cross-sectional evidence speaks for a steady decrease in happiness across age groups, but within-person decline in happiness was only evident in old age. Together the findings provide further evidence for multidirectional age differences in affective experience and suggest that the overall quality of affective experience may deteriorate in old age.</style></abstract><label><style face="normal" font="default" size="100%">subjective indicators</style></label><urls><pdf-urls><url>file://U:\SOEPLIT\Dokumente\7846_c.pdf</url></pdf-urls></urls><custom2><style face="normal" font="default" size="100%">longitudinal</style></custom2><custom4><style face="normal" font="default" size="100%">T08, T01</style></custom4><custom5><style face="normal" font="default" size="100%">02 SSCI Journal</style></custom5><custom6><style face="normal" font="default" size="100%">584</style></custom6><electronic-resource-num><style face="normal" font="default" size="100%">10.1037/a0033572</style></electronic-resource-num><remote-database-name><style face="normal" font="default" size="100%">SOEP</style></remote-database-name><remote-database-provider><style face="normal" font="default" size="100%">SOEP</style></remote-database-provider><language><style face="normal" font="default" size="100%">GB</style></language></record><record><database name="SOEPlit_master.enl" path="U:\SOEPLIT\Endnote\SOEPlit_master.enl">SOEPlit_master.enl</database><source-app name="EndNote" version="17.0">EndNote</source-app><rec-number>10435</rec-number><foreign-keys><key app="EN" db-id="sw9fd25xqxxt0xep9fbpf9zqrtpe5t9wz0wv">10435</key><key app="ENWeb" db-id="SL1BsQrtqggAAA5wtKQ">16611</key></foreign-keys><ref-type name="Journal Article">17</ref-type><contributors><authors><author><style face="normal" font="default" size="100%">Matiaske, Wenzel</style></author><author><style face="normal" font="default" size="100%">Menges, Roland</style></author><author><style face="normal" font="default" size="100%">Spiess, Martin</style></author></authors></contributors><titles><title><style face="normal" font="default" size="100%">Modifying the Rebound: It depends! Explaining Mobility Behaviour on the Basis of the German Socio-Economic Panel</style></title><secondary-title><style face="normal" font="default" size="100%">Energy Policy</style></secondary-title></titles><pages><style face="normal" font="default" size="100%">29-35</style></pages><volume><style face="normal" font="default" size="100%">41</style></volume><number><style face="normal" font="default" size="100%">1</style></number><section><style face="normal" font="default" size="100%">29</style></section><dates><year><style face="normal" font="default" size="100%">2012</style></year></dates><orig-pub><style face="normal" font="default" size="100%">2009: SOEPpapers 174. Berlin: DIW Berlin</style></orig-pub><accession-num><style face="normal" font="default" size="100%">5485</style></accession-num><call-num><style face="normal" font="default" size="100%">FALSCH</style></call-num><abstract><style face="normal" font="default" size="100%">We address the empirical question to which extent higher fuel efficiency of cars affects additional travel and how this behavioural aspect is modified by additional variables. The data set used to estimate a theoretical model of the rebound effect covers two panel waves, 1998 and 2003, taken from the German Socio-Economic Panel (SOEP). To take full advantage of the information in the data available, and to avoid problems due to possible selection effects, we estimated an unbalanced two-wave random effects panel model. Our results suggest that in line with the rebound hypothesis, there is a negative effect of car efficiency on the kilometers driven. That is, the lower the fuel consumption, the larger the driven distance. However, contrasting recent empirical literature about the rebound effect in the transportation sector, this seems to be true only for cars with a consumption of more than roughly eight liters per hundred kilometers. In addition, we find a positive diesel effect, which implies that owning a diesel engined car, has a positive effect on the driven distance. Both effects can be interpreted as support for the rebound hypothesis, although not in a simple linear way. Moreover, it can be shown that some “soft” variables such as certain attitudes towards the environment tend to amplify this non-linear rebound effect. Our results support the general direction of the rebound effect on households travel activities. But because of the remaining political relevance of the rebound effect, they also highlight the importance of accounting for additional behavioural variables which tend to influence individual mobility behaviour. Hence, the classical interpretation of the rebound as a linear effect of advances in fuel economy on individual travel has to be questioned.</style></abstract><label><style face="normal" font="default" size="100%">miscellaneous, econometrics</style></label><urls><related-urls><url><style face="normal" font="default" size="100%">http://www.diw.de/documents/publikationen/73/97799/diw_sp0174.pdf</style></url></related-urls></urls><custom2><style face="normal" font="default" size="100%">longitudinal</style></custom2><custom5><style face="normal" font="default" size="100%">02 SSCI Journal</style></custom5><custom6><style face="normal" font="default" size="100%">174</style></custom6><electronic-resource-num><style face="normal" font="default" size="100%">10.1016/j.enpol.2010.11.044</style></electronic-resource-num><remote-database-name><style face="normal" font="default" size="100%">INLA</style></remote-database-name><remote-database-provider><style face="normal" font="default" size="100%">SOEP</style></remote-database-provider><language><style face="normal" font="default" size="100%">GB</style></language></record><record><database name="SOEPlit_master.enl" path="U:\SOEPLIT\Endnote\SOEPlit_master.enl">SOEPlit_master.enl</database><source-app name="EndNote" version="17.0">EndNote</source-app><rec-number>7637</rec-number><foreign-keys><key app="EN" db-id="sw9fd25xqxxt0xep9fbpf9zqrtpe5t9wz0wv">7637</key><key app="ENWeb" db-id="SL1BsQrtqggAAA5wtKQ">13890</key></foreign-keys><ref-type name="Magazine Article">19</ref-type><contributors><authors><author><style face="normal" font="default" size="100%">o.V.,</style></author></authors></contributors><titles><title><style face="normal" font="default" size="100%">Großer Einfluss auf Frauenerwerbstätigkeit</style></title><secondary-title><style face="normal" font="default" size="100%">Böckler zum Bündnis</style></secondary-title></titles><pages><style face="normal" font="default" size="100%">5</style></pages><number><style face="normal" font="default" size="100%">25</style></number><dates><year><style face="normal" font="default" size="100%">2002</style></year></dates><accession-num><style face="normal" font="default" size="100%">2781</style></accession-num><call-num><style face="normal" font="default" size="100%">FALSCH</style></call-num><urls></urls><custom1><style face="normal" font="default" size="100%">81</style></custom1><custom2><style face="normal" font="default" size="100%">citation of SOEP results</style></custom2><custom3><style face="normal" font="default" size="100%">0</style></custom3><custom5><style face="normal" font="default" size="100%">60 Popular Publication</style></custom5><remote-database-name><style face="normal" font="default" size="100%">ZITA</style></remote-database-name><language><style face="normal" font="default" size="100%">D</style></language></record><record><database name="SOEPlit_master.enl" path="U:\SOEPLIT\Endnote\SOEPlit_master.enl">SOEPlit_master.enl</database><source-app name="EndNote" version="17.0">EndNote</source-app><rec-number>7483</rec-number><foreign-keys><key app="EN" db-id="sw9fd25xqxxt0xep9fbpf9zqrtpe5t9wz0wv">7483</key><key app="ENWeb" db-id="SL1BsQrtqggAAA5wtKQ">13736</key></foreign-keys><ref-type name="Generic">13</ref-type><contributors><authors><author><style face="normal" font="default" size="100%">Landeszentralbank in Berlin und Brandenburg,</style></author></authors></contributors><titles><title><style face="normal" font="default" size="100%">Jahresbericht 2001</style></title></titles><pages><style face="normal" font="default" size="100%">76</style></pages><dates><year><style face="normal" font="default" size="100%">2002</style></year></dates><pub-location><style face="normal" font="default" size="100%">Berlin</style></pub-location><publisher><style face="normal" font="default" size="100%">LZB Berlin-Brandenburg</style></publisher><accession-num><style face="normal" font="default" size="100%">2620</style></accession-num><call-num><style face="normal" font="default" size="100%">WAHR</style></call-num><urls></urls><custom1><style face="normal" font="default" size="100%">99</style></custom1><custom2><style face="normal" font="default" size="100%">citation of SOEP results</style></custom2><custom3><style face="normal" font="default" size="100%">0</style></custom3><custom5><style face="normal" font="default" size="100%">70 Other</style></custom5><remote-database-name><style face="normal" font="default" size="100%">ZITA</style></remote-database-name><language><style face="normal" font="default" size="100%">D</style></language></record><record><database name="SOEPlit_master.enl" path="U:\SOEPLIT\Endnote\SOEPlit_master.enl">SOEPlit_master.enl</database><source-app name="EndNote" version="17.0">EndNote</source-app><rec-number>7431</rec-number><foreign-keys><key app="EN" db-id="sw9fd25xqxxt0xep9fbpf9zqrtpe5t9wz0wv">7431</key><key app="ENWeb" db-id="SL1BsQrtqggAAA5wtKQ">13684</key></foreign-keys><ref-type name="Thesis">32</ref-type><contributors><authors><author><style face="normal" font="default" size="100%">Ziefle, Andrea Susanne</style></author></authors></contributors><titles><title><style face="normal" font="default" size="100%">Kind und Karriere? Eine empirische Analyse der kurz- und längerfristigen Folgen des Erziehungsurlaubs für den Einkommensverlauf von Frauen (Diplomarbeit)</style></title></titles><dates><year><style face="normal" font="default" size="100%">2001</style></year></dates><pub-location><style face="normal" font="default" size="100%">Mannheim</style></pub-location><publisher><style face="normal" font="default" size="100%">Fakultät für Sozialwissenschaften der Universität Mannheim</style></publisher><accession-num><style face="normal" font="default" size="100%">2565</style></accession-num><call-num><style face="normal" font="default" size="100%">WAHR</style></call-num><label><style face="normal" font="default" size="100%">labour, family and networks, gender </style></label><urls></urls><custom1><style face="normal" font="default" size="100%">22</style></custom1><custom2><style face="normal" font="default" size="100%">longitudinal</style></custom2><custom3><style face="normal" font="default" size="100%">0</style></custom3><custom4><style face="normal" font="default" size="100%">T01, T02</style></custom4><custom5><style face="normal" font="default" size="100%">41 B.A./M.A. Thesis</style></custom5><remote-database-name><style face="normal" font="default" size="100%">INLA</style></remote-database-name><remote-database-provider><style face="normal" font="default" size="100%">SOEP </style></remote-database-provider><language><style face="normal" font="default" size="100%">D</style></language></record><record><database name="SOEPlit_master.enl" path="U:\SOEPLIT\Endnote\SOEPlit_master.enl">SOEPlit_master.enl</database><source-app name="EndNote" version="17.0">EndNote</source-app><rec-number>7424</rec-number><foreign-keys><key app="EN" db-id="sw9fd25xqxxt0xep9fbpf9zqrtpe5t9wz0wv">7424</key><key app="ENWeb" db-id="SL1BsQrtqggAAA5wtKQ">13677</key></foreign-keys><ref-type name="Report">27</ref-type><contributors><authors><author><style face="normal" font="default" size="100%">Infratest Sozialforschung,</style></author></authors></contributors><titles><title><style face="normal" font="default" size="100%">SOEP 2001 – Methodenbericht zum Befragungsjahr 2001 (Welle 18) des Sozio-oekonomischen Panels</style></title><secondary-title><style face="normal" font="default" size="100%">SOEP Survey Papers 38: Series B</style></secondary-title></titles><dates><year><style face="normal" font="default" size="100%">2011</style></year></dates><pub-location><style face="normal" font="default" size="100%">Berlin</style></pub-location><publisher><style face="normal" font="default" size="100%">DIW/SOEP</style></publisher><orig-pub><style face="normal" font="default" size="100%">2002: München</style></orig-pub><accession-num><style face="normal" font="default" size="100%">2558</style></accession-num><call-num><style face="normal" font="default" size="100%">WAHR</style></call-num><urls><related-urls><url><style face="normal" font="default" size="100%">http://panel.gsoep.de/soep-docs/surveypapers/diw_ssp0038.pdf</style></url></related-urls><pdf-urls><url>file://U:\SOEPSurveyPapers\B_SurveyReports\Fertig\diw_ssp0038.pdf</url></pdf-urls></urls><custom2><style face="normal" font="default" size="100%">Technical documentation</style></custom2><custom4><style face="normal" font="default" size="100%">T11</style></custom4><custom5><style face="normal" font="default" size="100%">36 Infratest Report</style></custom5><custom6><style face="normal" font="default" size="100%">S38</style></custom6><remote-database-name><style face="normal" font="default" size="100%">FELD</style></remote-database-name><language><style face="normal" font="default" size="100%">D</style></language></record><record><database name="SOEPlit_master.enl" path="U:\SOEPLIT\Endnote\SOEPlit_master.enl">SOEPlit_master.enl</database><source-app name="EndNote" version="17.0">EndNote</source-app><rec-number>9708</rec-number><foreign-keys><key app="EN" db-id="sw9fd25xqxxt0xep9fbpf9zqrtpe5t9wz0wv">9708</key><key app="ENWeb" db-id="SL1BsQrtqggAAA5wtKQ">15924</key></foreign-keys><ref-type name="Book">6</ref-type><contributors><authors><author><style face="normal" font="default" size="100%">Boeckh, Jürgen</style></author><author><style face="normal" font="default" size="100%">Huster, Ernst-Ulrich</style></author><author><style face="normal" font="default" size="100%">Benz, Benjamin</style></author></authors></contributors><titles><title><style face="normal" font="default" size="100%">Sozialpolitik in Deutschland. Eine systematische Einführung</style></title></titles><pages><style face="normal" font="default" size="100%">269; 273</style></pages><dates><year><style face="normal" font="default" size="100%">2006</style></year></dates><pub-location><style face="normal" font="default" size="100%">Wiesbaden</style></pub-location><publisher><style face="normal" font="default" size="100%">VS Verlag für Sozialwissenschaften</style></publisher><accession-num><style face="normal" font="default" size="100%">2184</style></accession-num><call-num><style face="normal" font="default" size="100%">FALSCH</style></call-num><urls></urls><custom1><style face="normal" font="default" size="100%">83</style></custom1><custom2><style face="normal" font="default" size="100%">citation of SOEP results</style></custom2><custom3><style face="normal" font="default" size="100%">0</style></custom3><custom5><style face="normal" font="default" size="100%">11 Book</style></custom5><remote-database-name><style face="normal" font="default" size="100%">ZITA</style></remote-database-name><language><style face="normal" font="default" size="100%">D</style></language></record></records></xml>